pyhcrf/_algorithms.pyx
pyhcrf/_algorithms.cpython-35m-x86_64-linux-gnu.so
pyhcrf/__init__.py
pyhcrf/logaddexp.h
pyhcrf/_version.txt
pyhcrf-0.1.0.dist-info/RECORD
pyhcrf-0.1.0.dist-info/METADATA
pyhcrf-0.1.0.dist-info/top_level.txt
pyhcrf-0.1.0.dist-info/COPYING.md
pyhcrf-0.1.0.dist-info/WHEEL
