Metadata-Version: 2.1
Name: pyhcrf
Version: 0.1.0
Summary: A hidden (state) conditional random field (HCRF) implementation written in Python and Cython.
Home-page: https://github.com/althonos/pyhcrf
Author: Dirko Coetsee
Author-email: dpcoetsee@gmail.com
Maintainer: Martin Larralde
Maintainer-email: martin.larralde@embl.de
License: BSD-2-Clause
Project-URL: Changelog, https://github.com/althonos/pyhcrf/blob/master/CHANGELOG.md
Project-URL: Bug Tracker, https://github.com/althonos/pyhcrf/issues
Keywords: statistics,crf,classifier,hidden,nlp
Platform: any
Classifier: Development Status :: 4 - Beta
Classifier: Intended Audience :: Developers
Classifier: Intended Audience :: Science/Research
Classifier: License :: OSI Approved :: BSD License
Classifier: Programming Language :: Cython
Classifier: Programming Language :: Python
Classifier: Programming Language :: Python :: 3.5
Classifier: Programming Language :: Python :: 3.6
Classifier: Programming Language :: Python :: 3.7
Classifier: Programming Language :: Python :: 3.8
Classifier: Programming Language :: Python :: Implementation :: CPython
Classifier: Programming Language :: Python :: Implementation :: PyPy
Classifier: Topic :: Scientific/Engineering :: Mathematics
Requires-Dist: numpy (~=1.9)
Requires-Dist: scipy (~=1.0)
